groundit/__init__.py
groundit/config.py
groundit/confidence/confidence_extractor.py
groundit/confidence/logprobs_aggregators.py
groundit/confidence/models.py
groundit/reference/add_source_spans.py
groundit/reference/create_model_with_source.py
groundit/reference/models.py
groundit-0.1.6.dist-info/METADATA
groundit-0.1.6.dist-info/WHEEL
groundit-0.1.6.dist-info/licenses/LICENSE
groundit-0.1.6.dist-info/RECORD
