Metadata-Version: 2.4
Name: groundit
Version: 0.1.6
Summary: Groundit adds source references and confidence scores to ensure your AI outputs are verifiable and trustworthy.
Project-URL: Homepage, https://github.com/Sam1320/groundit
Project-URL: Repository, https://github.com/Sam1320/groundit
Project-URL: Issues, https://github.com/Sam1320/groundit/issues
Author: Sam Rodriguez
License-Expression: MIT
License-File: LICENSE
Keywords: audit,confidence,extraction,llm,references
Classifier: Development Status :: 4 - Beta
Classifier: License :: OSI Approved :: MIT License
Classifier: Operating System :: OS Independent
Classifier: Programming Language :: Python :: 3
Classifier: Programming Language :: Python :: 3.12
Classifier: Topic :: Scientific/Engineering :: Artificial Intelligence
Classifier: Topic :: Software Development :: Libraries :: Python Modules
Requires-Python: >=3.12
Requires-Dist: lark>=1.2.2
Requires-Dist: litellm>=1.73.2
Requires-Dist: pydantic>=2.11.5
